django_debug_request/__init__.py
django_debug_request/apps.py
django_debug_request/management/__init__.py
django_debug_request/management/commands/__init__.py
django_debug_request/management/commands/debug_request.py
django_debug_request-1.0.0.dist-info/METADATA
django_debug_request-1.0.0.dist-info/WHEEL
django_debug_request-1.0.0.dist-info/licenses/LICENSE
django_debug_request-1.0.0.dist-info/RECORD
