Metadata-Version: 2.3
Name: django-debug-request
Version: 1.0.0
Summary: Execute cURL-like commands with logging within your Django production environment.
Project-URL: Homepage, https://github.com/raphaelm/django-debug-request
Project-URL: Issues, https://github.com/raphaelm/django-debug-request/issues
Author-email: Raphael Michel <mail@raphaelmichel.de>
License-File: LICENSE
Classifier: License :: OSI Approved :: Apache Software License
Classifier: Operating System :: OS Independent
Classifier: Programming Language :: Python :: 3
Requires-Python: >=3.9
